AUTHORS
LICENSE
MANIFEST.in
README.rst
REQUIREMENTS
setup.py
bin/pypackager
pypackager/__init__.py
pypackager/base.py
pypackager/channel.py
pypackager/constants.py
pypackager/creator.py
pypackager/downloader.py
pypackager/exceptions.py
pypackager/extractor.py
pypackager/loaders.py
pypackager/packager.py
pypackager/render.py
pypackager/settings.py
pypackager/utils.py
pypackager/renderers/__init__.py
pypackager/template/.package.cfg
pypackager/template/AUTHORS
pypackager/template/MANIFEST.in
pypackager/template/README.rst
pypackager/template/REQUIREMENTS
pypackager/template/setup.py
pypackager/template/docs/Makefile
pypackager/template/docs/conf.py
pypackager/template/docs/index.rst
pypackager/template/tests/__init__.py
pypackager/template/{{package_name}}/__init__.py
python_packager.egg-info/PKG-INFO
python_packager.egg-info/SOURCES.txt
python_packager.egg-info/dependency_links.txt
python_packager.egg-info/requires.txt
python_packager.egg-info/top_level.txt
tests/__init__.py
tests/test_packager.py
tests/test_utils.py