Metadata-Version: 1.1
Name: python-packager
Version: 0.0.9
Summary: A command-line tool to create Python Packages.
Home-page: https://github.com/fcurella/python-packager
Author: Flavio Curella
Author-email: flavio.curella@gmail.com
License: MIT
Platform: UNKNOWN
Classifier: Development Status :: 3 - Alpha
Classifier: Environment :: Console
Classifier: Intended Audience :: Developers
Classifier: Intended Audience :: Information Technology
Classifier: License :: OSI Approved :: MIT License
Classifier: Operating System :: OS Independent
Classifier: Programming Language :: Python
